unencryptedsocket/__init__.py
unencryptedsocket/client.py
unencryptedsocket/server.py
unencryptedsocket/utils.py
unencryptedsocket/__metadata__/DISCLIAIMER.md
unencryptedsocket/__metadata__/LICENSE
unencryptedsocket/__metadata__/README.md
unencryptedsocket/__metadata__/__init__.py
unencryptedsocket/__metadata__/requirements.txt
unencryptedsocket-2.1.0.dist-info/METADATA
unencryptedsocket-2.1.0.dist-info/WHEEL
unencryptedsocket-2.1.0.dist-info/top_level.txt
unencryptedsocket-2.1.0.dist-info/RECORD
